ovos_ocp_deezer_plugin/__init__.py
ovos_ocp_deezer_plugin/config.py
ovos_ocp_deezer_plugin/version.py
ovos_ocp_deezer_plugin-0.0.1.dist-info/METADATA
ovos_ocp_deezer_plugin-0.0.1.dist-info/WHEEL
ovos_ocp_deezer_plugin-0.0.1.dist-info/entry_points.txt
ovos_ocp_deezer_plugin-0.0.1.dist-info/top_level.txt
ovos_ocp_deezer_plugin-0.0.1.dist-info/zip-safe
ovos_ocp_deezer_plugin-0.0.1.dist-info/RECORD
