Metadata-Version: 2.1
Name: ovos-ocp-deezer-plugin
Version: 0.0.1
Summary: OCP youtube stream extractor plugin
Home-page: https://github.com/OpenVoiceOS/ovos-ocp-deezer-plugin
Author: JarbasAi
Author-email: jarbasai@mailfence.com
License: Apache-2.0
Keywords: ovos ocp plugin
Platform: UNKNOWN
Requires-Dist: ovos-plugin-common-play
Requires-Dist: deezeridu
